diffios/__init__.py
diffios/compare.py
diffios/config.py
diffios/constants.py
diffios-0.0.9.dist-info/DESCRIPTION.rst
diffios-0.0.9.dist-info/METADATA
diffios-0.0.9.dist-info/RECORD
diffios-0.0.9.dist-info/WHEEL
diffios-0.0.9.dist-info/metadata.json
diffios-0.0.9.dist-info/top_level.txt
