Metadata-Version: 2.0
Name: diffios
Version: 0.0.9
Summary: Compare Cisco IOS configurations against a template.
Home-page: https://github.com/robphoenix/diffios
Author: Rob Phoenix
Author-email: rob@robphoenix.com
License: MIT
Platform: UNKNOWN
Classifier: Development Status :: 3 - Alpha
Classifier: Programming Language :: Python :: 2
Classifier: Programming Language :: Python :: 2.7
Classifier: Programming Language :: Python :: 3
Classifier: Programming Language :: Python :: 3.3
Classifier: Programming Language :: Python :: 3.4
Classifier: Programming Language :: Python :: 3.5
Classifier: Programming Language :: Python :: 3.6
Classifier: License :: OSI Approved :: MIT License
